dacrawler/__init__.py
dacrawler/dd_amazon.py
dacrawler/ec2.py
dacrawler/parse.py
dacrawler/s3.py
dacrawler/scrap.py
dacrawler-1.0.29.dist-info/METADATA
dacrawler-1.0.29.dist-info/RECORD
dacrawler-1.0.29.dist-info/WHEEL
dacrawler-1.0.29.dist-info/top_level.txt
